mouse_jiggler/__init__.py
mouse_jiggler/args_.py
mouse_jiggler/jiggler.py
mouse_jiggler_advanced-1.0.4.dist-info/METADATA
mouse_jiggler_advanced-1.0.4.dist-info/WHEEL
mouse_jiggler_advanced-1.0.4.dist-info/entry_points.txt
mouse_jiggler_advanced-1.0.4.dist-info/top_level.txt
mouse_jiggler_advanced-1.0.4.dist-info/RECORD
