Metadata-Version: 2.1
Name: mouse_jiggler_advanced
Version: 1.0.4
Summary: A script to move the cursor randomly to prevent idle detection.
Home-page: https://github.com/hurryingauto3/mouse_jiggler
Author: Ali Hamza
Author-email: alihamza19999@gmail.com
Classifier: Programming Language :: Python :: 3
Classifier: License :: OSI Approved :: MIT License
Classifier: Operating System :: OS Independent
Requires-Python: >=3.6
Requires-Dist: pytz
Requires-Dist: pyautogui
